KmerGenerator/__init__.py
KmerGenerator/kmerGenerator.py
kmerGenerator/__init__.py
kmerGenerator/kmerGenerator.py
KmerGenerator-0.0.4.dist-info/METADATA
KmerGenerator-0.0.4.dist-info/WHEEL
KmerGenerator-0.0.4.dist-info/top_level.txt
KmerGenerator-0.0.4.dist-info/RECORD
