Metadata-Version: 2.1
Name: KmerGenerator
Version: 0.0.4
Summary: UNKNOWN
Home-page: https://github.com/sgelias/kmer-generator.git
Author: Samuel Galva\~o Elias
Author-email: sgelias@outlook.com
License: UNKNOWN
Keywords: k-mers,DNA-Sequences,Biological-Sequences
Platform: UNKNOWN
Classifier: Programming Language :: Python :: 3
Classifier: License :: OSI Approved :: MIT License
Classifier: Operating System :: OS Independent
Requires-Python: >=3.6
